porringer_core-0.1.1.dev10.dist-info/METADATA
porringer_core-0.1.1.dev10.dist-info/WHEEL
porringer_core-0.1.1.dev10.dist-info/licenses/LICENSE.md
porringer_core/__init__.py
porringer_core/plugin_schema/__init__.py
porringer_core/plugin_schema/environment.py
porringer_core/py.typed
porringer_core/schema.py
porringer_core-0.1.1.dev10.dist-info/RECORD
